bytetrie/__init__.py
bytetrie/bytetrie.py
bytetrie/util.py
bytetrie-0.1.0.dist-info/LICENSE
bytetrie-0.1.0.dist-info/METADATA
bytetrie-0.1.0.dist-info/WHEEL
bytetrie-0.1.0.dist-info/top_level.txt
bytetrie-0.1.0.dist-info/RECORD
