Metadata-Version: 2.1
Name: bytetrie
Version: 0.1.0
Summary: A self-compressing, dependency-free radix trie
Home-page: https://git.friedl.net/incubator/bytetrie
Author: Armin Friedl
Author-email: dev@friedl.net
License: MIT
Platform: UNKNOWN
Classifier: License :: OSI Approved :: MIT License
Classifier: Programming Language :: Python :: 3
Classifier: Programming Language :: Python :: 3.7
